cli/__init__.py
cli/cli.py
janarthana_own_cli-0.1.dist-info/METADATA
janarthana_own_cli-0.1.dist-info/WHEEL
janarthana_own_cli-0.1.dist-info/entry_points.txt
janarthana_own_cli-0.1.dist-info/top_level.txt
janarthana_own_cli-0.1.dist-info/RECORD
