Metadata-Version: 2.1
Name: janarthana_own_cli
Version: 0.1
Summary: created own CLI for practice
Author: Janarthana
Author-email: janarthana.life@gmail.com
Classifier: Programming Language :: Python :: 3
Classifier: License :: OSI Approved :: MIT License
Classifier: Operating System :: OS Independent
Requires-Python: >=3.6
